universal_memory/__init__.py
universal_memory/client.py
universal_memory/cli/__init__.py
universal_memory/cli/main.py
universal_memory/cloud/__init__.py
universal_memory/cloud/deployment.py
universal_memory/cloud/providers.py
ragmax-1.0.0.dist-info/METADATA
ragmax-1.0.0.dist-info/WHEEL
ragmax-1.0.0.dist-info/entry_points.txt
ragmax-1.0.0.dist-info/top_level.txt
ragmax-1.0.0.dist-info/RECORD
