Metadata-Version: 2.4
Name: ragmax
Version: 1.0.0
Summary: RAGMax - Advanced RAG memory system for AI platforms via MCP
Home-page: https://github.com/yourusername/ragmax
Author: Vish Siddharth
Author-email: Vish Siddharth <your.email@example.com>
License: MIT
Project-URL: Homepage, https://github.com/yourusername/ragmax
Project-URL: Documentation, https://github.com/yourusername/ragmax#readme
Project-URL: Repository, https://github.com/yourusername/ragmax
Project-URL: Issues, https://github.com/yourusername/ragmax/issues
Keywords: ai,memory,mcp,claude,chatgpt,rag,vector-search
Classifier: Development Status :: 4 - Beta
Classifier: Intended Audience :: Developers
Classifier: Topic :: Software Development :: Libraries :: Python Modules
Classifier: License :: OSI Approved :: MIT License
Classifier: Programming Language :: Python :: 3
Classifier: Programming Language :: Python :: 3.8
Classifier: Programming Language :: Python :: 3.9
Classifier: Programming Language :: Python :: 3.10
Classifier: Programming Language :: Python :: 3.11
Classifier: Programming Language :: Python :: 3.12
Requires-Python: >=3.8
Requires-Dist: docker>=6.0.0
Requires-Dist: pyyaml>=6.0
Requires-Dist: requests>=2.31.0
Requires-Dist: click>=8.1.0
Requires-Dist: rich>=13.0.0
Requires-Dist: python-dotenv>=1.0.0
Provides-Extra: cloud
Requires-Dist: boto3>=1.28.0; extra == "cloud"
Requires-Dist: google-cloud-storage>=2.10.0; extra == "cloud"
Requires-Dist: azure-storage-blob>=12.19.0; extra == "cloud"
Provides-Extra: dev
Requires-Dist: pytest>=7.0.0; extra == "dev"
Requires-Dist: black>=22.0.0; extra == "dev"
Requires-Dist: flake8>=4.0.0; extra == "dev"
Requires-Dist: mypy>=0.950; extra == "dev"
Dynamic: author
Dynamic: home-page
Dynamic: requires-python
